aiohttp_apigami/__init__.py
aiohttp_apigami/constants.py
aiohttp_apigami/core.py
aiohttp_apigami/data.py
aiohttp_apigami/middlewares.py
aiohttp_apigami/plugin.py
aiohttp_apigami/py.typed
aiohttp_apigami/route_processor.py
aiohttp_apigami/swagger_ui.py
aiohttp_apigami/typedefs.py
aiohttp_apigami/utils.py
aiohttp_apigami/validation.py
aiohttp_apigami/decorators/__init__.py
aiohttp_apigami/decorators/docs.py
aiohttp_apigami/decorators/request.py
aiohttp_apigami/decorators/response.py
aiohttp_apigami/swagger_ui/VERSION
aiohttp_apigami/swagger_ui/favicon-16x16.png
aiohttp_apigami/swagger_ui/favicon-32x32.png
aiohttp_apigami/swagger_ui/index.css
aiohttp_apigami/swagger_ui/index.html
aiohttp_apigami/swagger_ui/oauth2-redirect.html
aiohttp_apigami/swagger_ui/oauth2-redirect.js
aiohttp_apigami/swagger_ui/swagger-initializer.js
aiohttp_apigami/swagger_ui/swagger-ui-bundle.js
aiohttp_apigami/swagger_ui/swagger-ui-es-bundle-core.js
aiohttp_apigami/swagger_ui/swagger-ui-es-bundle.js
aiohttp_apigami/swagger_ui/swagger-ui-standalone-preset.js
aiohttp_apigami/swagger_ui/swagger-ui.css
aiohttp_apigami/swagger_ui/swagger-ui.js
aiohttp_apigami-0.5.7.dist-info/METADATA
aiohttp_apigami-0.5.7.dist-info/WHEEL
aiohttp_apigami-0.5.7.dist-info/licenses/LICENSE
aiohttp_apigami-0.5.7.dist-info/RECORD
